wix_utils/__init__.py
wix_utils/generate_wxi.py
wix_utils-0.1.dist-info/DESCRIPTION.rst
wix_utils-0.1.dist-info/METADATA
wix_utils-0.1.dist-info/RECORD
wix_utils-0.1.dist-info/WHEEL
wix_utils-0.1.dist-info/metadata.json
wix_utils-0.1.dist-info/top_level.txt
